bbc1/__init__.py
bbc1/core/__init__.py
bbc1/core/bbc_app.py
bbc1/core/bbc_config.py
bbc1/core/bbc_core.py
bbc1/core/bbc_error.py
bbc1/core/bbc_network.py
bbc1/core/bbc_stats.py
bbc1/core/bbclib.py
bbc1/core/command.py
bbc1/core/data_handler.py
bbc1/core/domain0_manager.py
bbc1/core/key_exchange_manager.py
bbc1/core/logger.py
bbc1/core/message_key_types.py
bbc1/core/query_management.py
bbc1/core/repair_manager.py
bbc1/core/topology_manager.py
bbc1/core/user_message_routing.py
bbc1-1.5.1.data/scripts/bbc_core.py
bbc1-1.5.1.data/scripts/bbc_domain_config.py
bbc1-1.5.1.data/scripts/bbc_domain_update.py
bbc1-1.5.1.data/scripts/bbc_info.py
bbc1-1.5.1.data/scripts/bbc_ping.py
bbc1-1.5.1.data/scripts/db_migration_tool.py
bbc1-1.5.1.data/scripts/domain_key_setup.py
bbc1-1.5.1.data/scripts/file_proof.py
bbc1-1.5.1.data/scripts/id_create.py
bbc1-1.5.1.dist-info/AUTHORS
bbc1-1.5.1.dist-info/LICENSE
bbc1-1.5.1.dist-info/METADATA
bbc1-1.5.1.dist-info/WHEEL
bbc1-1.5.1.dist-info/top_level.txt
bbc1-1.5.1.dist-info/RECORD
