Metadata-Version: 2.1
Name: bbc1
Version: 1.5.1
Summary: A core system of Beyond Blockchain One
Home-page: https://github.com/beyond-blockchain/bbc1
Author: beyond-blockchain.org
Author-email: bbc1-dev@beyond-blockchain.org
License: Apache License 2.0
Platform: UNKNOWN
Classifier: Development Status :: 4 - Beta
Classifier: Programming Language :: Python :: 3.5
Classifier: Programming Language :: Python :: 3.6
Classifier: Programming Language :: Python :: 3.7
Classifier: Topic :: Software Development
Requires-Dist: pyOpenSSL (>=16.2.0)
Requires-Dist: jinja2 (>=2.8.1)
Requires-Dist: requests (>=2.12.4)
Requires-Dist: gevent (>=1.2.1)
Requires-Dist: cryptography (>=2.1.4)
Requires-Dist: pytest (>=5.3.0)
Requires-Dist: msgpack-python (>=0.4.8)
Requires-Dist: mysql-connector-python (>=8.0.5)
Requires-Dist: py-bbclib (>=1.6)
Requires-Dist: greenlet
Requires-Dist: bson
Requires-Dist: Flask (<=1.0.1,>=0.10.1)
